Assignments/Assignment_2/yosys_codes/fsm.v
module fsm (
 input clk,             //Clock signal
 input reset,           //Reset signal
 input [1:0] in,        //2-bit input signal
 output reg [1:0] out   //2-bit output signal
);

//States
parameter S1 = 3'b000;
parameter S2 = 3'b001;
parameter S3 = 3'b010;
parameter S4 = 3'b011;
parameter S5 = 3'b100;

//State reg and next state reg
reg [2:0] state_reg, next_reg;

//State transition
always @(posedge clk or posedge reset) begin
 if (reset) begin
 state_reg <= S1;  //Reset to initial state S1
 end else begin
 state_reg <= next_reg;  //Transition to next state
 end
 end

always @(*) begin
 //Default values
 next_reg=state_reg;
 out=2'b00;

 //Switch cases for states and outputs
 case (state_reg)
 S1: begin
 case (in)
 2'b00: begin
 out=2'b01;
 next_reg=S1;
 end
 2'b01: begin
 out=2'b00;
 next_reg=S1;
 end
 2'b10: begin
 out=2'b01;
 next_reg=S2;
 end
 2'b11: begin
 out=2'b00;
 next_reg=S3;
 end
 endcase
 end
 S2: begin
 case (in)
 2'b00: begin
 out=2'b11;
 next_reg=S1;
 end
 2'b01: begin
 out=2'b11;
 next_reg=S3;
 end
 2'b10: begin
 out=2'b10;
 next_reg=S2;
 end
 2'b11: begin
 out=2'b10;
 next_reg=S4;
 end
 endcase
 end
 S3: begin
 case (in)
 2'b00: begin
 out=2'b00;
 next_reg=S1;
 end
 2'b01: begin
 out=2'b01;
 next_reg=S5;
 end
 2'b10: begin
 out=2'b00;
 next_reg=S3;
 end
 2'b11: begin
 out=2'b00;
 next_reg=S4;
 end
 endcase
 end
 S4: begin
 case (in)
 2'b00: begin
 out=2'b11;
 next_reg=S3;
 end
 2'b01: begin
 out=2'b01;
 next_reg=S5;
 end
 2'b10: begin
 out=2'b01;
 next_reg=S5;
 end
 2'b11: begin
 out=2'b11;
 next_reg=S4;
 end
 endcase
 end
 S5: begin
 case (in)
 2'b00: begin
 out=2'b00;
 next_reg=S5;
 end
 2'b01: begin
 out=2'b00;
 next_reg=S1;
 end
 2'b10: begin
 out=2'b10;
 next_reg=S1;
 end
 2'b11: begin
 out=2'b11;
 next_reg=S5;
 end
 endcase
 end
 endcase
end
endmodule

Assignments/Assignment_2/icarus_codes/fsm_tb.v
module fsm_tb;
 reg clk;
 reg reset;
 reg [1:0] in;
 wire [1:0] out;
 
 //Instantiate our verilog top level fsm
 fsm dut(
 .clk(clk),
 .reset(reset),
 .in(in),
 .out(out)
 );
 
 //Generating clk
 initial 
 begin
 clk=0;
 forever #10 clk = ~clk;    //To toggle it always
 end
 
 //Tests
 initial 
 begin
 
 $dumpfile("fsm.vcd");      //Dumpfile
 $dumpvars(0,fsm_tb);
 
 //Defining reset and in
 reset = 1; in = 2'b00;
 #20 reset = 0;
 
 //All possible paths are tested by input combinations
 #20 in=2'b00; //S1
 #20 in=2'b01; //S1
 #20 in=2'b10; //S2
 #20 in=2'b10; //S2
 #20 in=2'b01; //S3
 #20 in=2'b10; //S3
 #20 in=2'b11; //S4
 #20 in=2'b11; //S4
 #20 in=2'b10; //S5
 #20 in=2'b00; //S5
 #20 in=2'b11; //S5
 #20 in=2'b01; //S1
 
 reset=1;
 #0.5 reset=0;
 
 #20 in=2'b11; //S3
 #20 in=2'b00; //S1
 #20 in=2'b11; //S3
 #20 in=2'b01; //S5
 #20 in=2'b10; //S1
 
 reset=1;
 #0.5 reset=0;
 
 #20 in=2'b10; //S2
 #20 in=2'b00; //S1
 #20 in=2'b11; //S3
 #20 in=2'b01; //S5
 #20 in=2'b01; //S1
 
 reset=1;
 #0.5 reset=0;
 
 #20 in=2'b10; //S2
 #20 in=2'b10; //S2
 #20 in=2'b11; //S4
 #20 in=2'b00; //S3
 #20 in=2'b11; //S4
 #20 in=2'b01; //S5
 #20 in=2'b10; //S1
 
 reset=1;
 #0.5 reset=0;
 
 #20 in=2'b10;
 #20 in=2'b10;
 #20 in=2'b01;
 #20 in=2'b00;
 #20 in=2'b01;
 #20 in=2'b11;
 #20 in=2'b11;
 #20 in=2'b00;
 #20 in=2'b01;
 #20 in=2'b00;
 #20 in=2'b01;

 //End simulation
 #10 $finish;
 end
 
 //signal verification
 always @(posedge clk or posedge reset) begin
 if (reset) begin
 end else begin
 end
 end
endmodule

Assignments/Assignment_2/icarus_codes/fsm.vcd
$date
	Tue Sep 24 15:24:59 2024
$end
$version
	Icarus Verilog
$end
$timescale
	1s
$end
$scope module fsm_tb $end
$var wire 2 ! out [1:0] $end
$var reg 1 " clk $end
$var reg 2 # in [1:0] $end
$var reg 1 $ reset $end
$scope module dut $end
$var wire 1 " clk $end
$var wire 2 % in [1:0] $end
$var wire 1 $ reset $end
$var reg 3 & next_reg [2:0] $end
$var reg 2 ' out [1:0] $end
$var reg 3 ( state_reg [2:0] $end
$upscope $end
$upscope $end
$enddefinitions $end
#0
$dumpvars
b0 (
b1 '
b0 &
b0 %
1$
b0 #
0"
b1 !
$end
#10
1"
#20
0"
0$
#30
1"
#40
0"
#50
1"
#60
b0 !
b0 '
0"
b1 #
b1 %
#70
1"
#80
b1 &
b1 !
b1 '
0"
b10 #
b10 %
#90
b10 !
b10 '
b1 (
1"
#100
0"
#110
1"
#120
b10 &
b11 !
b11 '
0"
b1 #
b1 %
#130
b100 &
b1 !
b1 '
b10 (
1"
#140
b0 !
b0 '
b10 &
0"
b10 #
b10 %
#150
1"
#160
b11 &
0"
b11 #
b11 %
#170
b11 !
b11 '
b11 (
1"
#180
0"
#190
1"
#200
b100 &
b1 !
b1 '
0"
b10 #
b10 %
#210
b0 &
b10 !
b10 '
b100 (
1"
#220
b0 !
b0 '
b100 &
0"
b0 #
b0 %
#230
1"
#240
b11 !
b11 '
0"
b11 #
b11 %
#250
1"
#260
b0 (
b0 &
b0 !
b0 '
0"
1$
b1 #
b1 %
#261
0$
#270
1"
#280
0"
#281
b10 &
b11 #
b11 %
#290
b11 &
b10 (
1"
#300
0"
#301
b0 &
b0 #
b0 %
#310
b1 !
b1 '
b0 (
1"
#320
0"
#321
b10 &
b0 !
b0 '
b11 #
b11 %
#330
b11 &
b10 (
1"
#340
0"
#341
b1 !
b1 '
b100 &
b1 #
b1 %
#350
b0 &
b0 !
b0 '
b100 (
1"
#360
0"
#361
b0 (
b1 !
b1 '
b1 &
1$
b10 #
b10 %
#362
0$
#370
b10 !
b10 '
b1 (
1"
#380
0"
#390
1"
#400
0"
#402
b0 &
b11 !
b11 '
b0 #
b0 %
#410
b1 !
b1 '
b0 (
1"
#420
0"
#422
b10 &
b0 !
b0 '
b11 #
b11 %
#430
b11 &
b10 (
1"
#440
0"
#442
b1 !
b1 '
b100 &
b1 #
b1 %
#450
b0 &
b0 !
b0 '
b100 (
1"
#460
0"
#462
b0 (
1$
#463
0$
#470
1"
#480
0"
#483
b1 &
b1 !
b1 '
b10 #
b10 %
#490
b10 !
b10 '
b1 (
1"
#500
0"
#510
1"
#520
0"
#523
b11 &
b10 !
b10 '
b11 #
b11 %
#530
b11 !
b11 '
b11 (
1"
#540
0"
#543
b10 &
b11 !
b11 '
b0 #
b0 %
#550
b0 &
b0 !
b0 '
b10 (
1"
#560
0"
#563
b11 &
b11 #
b11 %
#570
b11 !
b11 '
b11 (
1"
#580
0"
#583
b100 &
b1 !
b1 '
b1 #
b1 %
#590
b0 &
b0 !
b0 '
b100 (
1"
#600
0"
#603
b0 (
b1 !
b1 '
b1 &
1$
b10 #
b10 %
#604
0$
#610
b10 !
b10 '
b1 (
1"
#620
0"
#630
1"
#640
0"
#650
1"
#660
0"
#664
b10 &
b11 !
b11 '
b1 #
b1 %
#670
b100 &
b1 !
b1 '
b10 (
1"
#680
0"
#684
b0 !
b0 '
b0 &
b0 #
b0 %
#690
b1 !
b1 '
b0 (
1"
#700
0"
#704
b0 !
b0 '
b1 #
b1 %
#710
1"
#720
0"
#724
b10 &
b11 #
b11 %
#730
b11 &
b10 (
1"
#740
0"
#750
b11 !
b11 '
b11 (
1"
#760
0"
#764
b10 &
b11 !
b11 '
b0 #
b0 %
#770
b0 &
b0 !
b0 '
b10 (
1"
#780
0"
#784
b1 !
b1 '
b100 &
b1 #
b1 %
#790
b0 &
b0 !
b0 '
b100 (
1"
#800
0"
#804
b100 &
b0 #
b0 %
#810
1"
#820
0"
#824
b0 &
b1 #
b1 %
#830
b0 (
1"
